gbcall/__init__.py
gbcall/callWithTypeCheck.py
gbcall/cli.py
gbcall/handler.py
gbcall/scanner.py
gbcall/server.py
gbcall/settings.py
gbcall/typeConverter.py
gbcall/types.py
gbcall/utils.py
global_call_browser-0.0.36.dist-info/LICENSE
global_call_browser-0.0.36.dist-info/METADATA
global_call_browser-0.0.36.dist-info/WHEEL
global_call_browser-0.0.36.dist-info/top_level.txt
global_call_browser-0.0.36.dist-info/RECORD
