Metadata-Version: 2.1
Name: global-call-browser
Version: 0.0.36
Summary: A simple serverless function transformer,     and a simple way to call function in other language.
Home-page: UNKNOWN
Author: bi1lqv
Author-email: bi1lqy.y@gmail.com
License: MIT
Platform: UNKNOWN
